invenio_jobs/__init__.py
invenio_jobs/api.py
invenio_jobs/cli.py
invenio_jobs/config.py
invenio_jobs/errors.py
invenio_jobs/ext.py
invenio_jobs/jobs.py
invenio_jobs/models.py
invenio_jobs/proxies.py
invenio_jobs/registry.py
invenio_jobs/tasks.py
invenio_jobs/utils.py
invenio_jobs/views.py
invenio_jobs/webpack.py
invenio_jobs/administration/__init__.py
invenio_jobs/administration/jobs.py
invenio_jobs/administration/runs.py
invenio_jobs/alembic/1753948224_add_subtasks_columns_to_jobs_run.py
invenio_jobs/alembic/1757597048_add_run_args_column_to_jobs_job_table.py
invenio_jobs/alembic/1f896f6990b8_update_jobs_module_table_names.py
invenio_jobs/alembic/356496a01197_create_invenio_jobs_tables.py
invenio_jobs/alembic/371f4cbcb73d_create_invenio_jobs_branch.py
invenio_jobs/alembic/9732b5f7609a_change_datetime_types.py
invenio_jobs/assets/semantic-ui/js/invenio_jobs/administration/JobActions.js
invenio_jobs/assets/semantic-ui/js/invenio_jobs/administration/JobDetailsView.js
invenio_jobs/assets/semantic-ui/js/invenio_jobs/administration/JobRunsHeader.js
invenio_jobs/assets/semantic-ui/js/invenio_jobs/administration/JobSearchLayout.js
invenio_jobs/assets/semantic-ui/js/invenio_jobs/administration/JobSearchResultItemLayout.js
invenio_jobs/assets/semantic-ui/js/invenio_jobs/administration/RunActionForm.js
invenio_jobs/assets/semantic-ui/js/invenio_jobs/administration/RunsLogs.js
invenio_jobs/assets/semantic-ui/js/invenio_jobs/administration/RunsLogsView.js
invenio_jobs/assets/semantic-ui/js/invenio_jobs/administration/RunsSearchResultItemLayout.js
invenio_jobs/assets/semantic-ui/js/invenio_jobs/administration/ScheduleJobModal.js
invenio_jobs/assets/semantic-ui/js/invenio_jobs/administration/StatusFormatter.js
invenio_jobs/assets/semantic-ui/js/invenio_jobs/administration/StopButton.js
invenio_jobs/assets/semantic-ui/js/invenio_jobs/administration/index.js
invenio_jobs/assets/semantic-ui/js/invenio_jobs/administration/utils/diffTimestamps.js
invenio_jobs-7.0.0.dist-info/licenses/AUTHORS.rst
invenio_jobs-7.0.0.dist-info/licenses/LICENSE
invenio_jobs-7.0.0.dist-info/METADATA
invenio_jobs-7.0.0.dist-info/WHEEL
invenio_jobs-7.0.0.dist-info/entry_points.txt
invenio_jobs-7.0.0.dist-info/top_level.txt
invenio_jobs-7.0.0.dist-info/RECORD
